README.md
setup.py
activity_client/__init__.py
activity_client.egg-info/PKG-INFO
activity_client.egg-info/SOURCES.txt
activity_client.egg-info/dependency_links.txt
activity_client.egg-info/requires.txt
activity_client.egg-info/top_level.txt
activity_client/client/__init__.py
activity_client/client/activity.py
activity_client/client/base.py