Metadata-Version: 1.0
Name: activity-client
Version: 0.0.1
Summary: cloud activity API client library.
Home-page: UNKNOWN
Author: mingl_wang
Author-email: wangminglu_1908@163.com
License: UNKNOWN
Platform: UNKNOWN
